euler_swarm/__init__.py
euler_swarm/create_graph.py
euler_swarm/level_segregation.py
euler_swarm/main.py
euler_swarm-0.2.1.dist-info/LICENSE
euler_swarm-0.2.1.dist-info/METADATA
euler_swarm-0.2.1.dist-info/WHEEL
euler_swarm-0.2.1.dist-info/entry_points.txt
euler_swarm-0.2.1.dist-info/top_level.txt
euler_swarm-0.2.1.dist-info/RECORD
